{
    "released_at":  "2026-06-28",
    "requires_database_migration":  false,
    "rollback":  {
                     "frontend":  "bosesanjit/orbitsm-frontend:1.0.4",
                     "backend":  "bosesanjit/orbitsm-backend:1.0.4"
                 },
    "version":  "1.0.5",
    "update_type":  "patch",
    "tags":  {
                 "latest":  "1.0.5",
                 "stable":  "1.0.5",
                 "rollback":  "1.0.4"
             },
    "images":  {
                   "reverse_proxy":  "nginx:1.27-alpine",
                   "backend":  "bosesanjit/orbitsm-backend:1.0.5",
                   "database":  "postgres:15",
                   "frontend":  "bosesanjit/orbitsm-frontend:1.0.5"
               },
    "channel":  "stable",
    "health_check_url":  "/health",
    "minimum_supported_version":  "1.0.4",
    "notes":  [
                  "Adds Docker Hub public registry option in Update Center.",
                  "Adds Microsoft 365 SMTP, Gmail/Workspace SMTP, Company mail relay, and IIS SMTP relay presets.",
                  "Keeps previous version 1.0.4 available as rollback target."
              ]
}
